email_safeguard/__init__.py
email_safeguard/validator.py
email_safeguard/data/disposable_domains.txt
email_safeguard/data/popular_domains.txt
email_safeguard/data/popular_tlds.txt
tests/__init__.py
tests/test_validator.py
email_safeguard-0.1.8.dist-info/LICENSE
email_safeguard-0.1.8.dist-info/METADATA
email_safeguard-0.1.8.dist-info/WHEEL
email_safeguard-0.1.8.dist-info/top_level.txt
email_safeguard-0.1.8.dist-info/RECORD
