Metadata-Version: 2.1
Name: email-safeguard
Version: 0.1.8
Summary: A Python library for validating and suggesting corrections for email addresses.
Home-page: https://github.com/chukaibejih/email-validator
Author: Chukwuka Ibejih
Author-email: chukaibejih@gmail.com
Classifier: Programming Language :: Python :: 3
Classifier: License :: OSI Approved :: MIT License
Classifier: Operating System :: OS Independent
Requires-Python: >=3.6
License-File: LICENSE
Requires-Dist: django >=3.0
Requires-Dist: python-Levenshtein
Requires-Dist: dnspython
